pydra/tasks/afni/__init__.py
pydra/tasks/afni/_version.py
pydra/tasks/afni/latest.py
pydra/tasks/afni/auto/__init__.py
pydra/tasks/afni/auto/_post_release.py
pydra/tasks/afni/auto/base.py
pydra/tasks/afni/auto/model/__init__.py
pydra/tasks/afni/auto/model/deconvolve.py
pydra/tasks/afni/auto/model/remlfit.py
pydra/tasks/afni/auto/model/synthesize.py
pydra/tasks/afni/auto/model/tests/conftest.py
pydra/tasks/afni/auto/model/tests/test_deconvolve.py
pydra/tasks/afni/auto/model/tests/test_remlfit.py
pydra/tasks/afni/auto/model/tests/test_synthesize.py
pydra/tasks/afni/auto/nipype_ports/__init__.py
pydra/tasks/afni/auto/nipype_ports/interfaces/__init__.py
pydra/tasks/afni/auto/nipype_ports/interfaces/base/__init__.py
pydra/tasks/afni/auto/nipype_ports/interfaces/base/core.py
pydra/tasks/afni/auto/preprocess/__init__.py
pydra/tasks/afni/auto/preprocess/align_epi_anat_py.py
pydra/tasks/afni/auto/preprocess/allineate.py
pydra/tasks/afni/auto/preprocess/auto_t_l_r_c.py
pydra/tasks/afni/auto/preprocess/auto_tcorrelate.py
pydra/tasks/afni/auto/preprocess/auto_tlrc.py
pydra/tasks/afni/auto/preprocess/automask.py
pydra/tasks/afni/auto/preprocess/bandpass.py
pydra/tasks/afni/auto/preprocess/blur_in_mask.py
pydra/tasks/afni/auto/preprocess/blur_to_f_w_h_m.py
pydra/tasks/afni/auto/preprocess/blur_to_fwhm.py
pydra/tasks/afni/auto/preprocess/clip_level.py
pydra/tasks/afni/auto/preprocess/degree_centrality.py
pydra/tasks/afni/auto/preprocess/despike.py
pydra/tasks/afni/auto/preprocess/detrend.py
pydra/tasks/afni/auto/preprocess/ecm.py
pydra/tasks/afni/auto/preprocess/fim.py
pydra/tasks/afni/auto/preprocess/fourier.py
pydra/tasks/afni/auto/preprocess/hist.py
pydra/tasks/afni/auto/preprocess/lfcd.py
pydra/tasks/afni/auto/preprocess/maskave.py
pydra/tasks/afni/auto/preprocess/means.py
pydra/tasks/afni/auto/preprocess/net_corr.py
pydra/tasks/afni/auto/preprocess/outlier_count.py
pydra/tasks/afni/auto/preprocess/quality_index.py
pydra/tasks/afni/auto/preprocess/qwarp.py
pydra_afni-0.3.2.dist-info/METADATA
pydra_afni-0.3.2.dist-info/WHEEL
pydra_afni-0.3.2.dist-info/licenses/LICENSE
pydra_afni-0.3.2.dist-info/RECORD
